m_phate/__init__.py
m_phate/data.py
m_phate/kernel.py
m_phate/m_phate.py
m_phate/train.py
m_phate/utils.py
m_phate/version.py
m_phate-0.1.6.dist-info/LICENSE
m_phate-0.1.6.dist-info/METADATA
m_phate-0.1.6.dist-info/WHEEL
m_phate-0.1.6.dist-info/top_level.txt
m_phate-0.1.6.dist-info/RECORD
