Metadata-Version: 2.1
Name: m-phate
Version: 0.1.6
Summary: m-phate
Home-page: https://github.com/scottgigante/m-phate
Author: Scott Gigante, Yale University
Author-email: scott.gigante@yale.edu
License: GNU General Public License Version 3
Download-URL: https://github.com/scottgigante/m-phate/archive/v0.1.6.tar.gz
Keywords: big-data,computational-biology
Platform: UNKNOWN
Classifier: Development Status :: 4 - Beta
Classifier: Environment :: Console
Classifier: Framework :: Jupyter
Classifier: Intended Audience :: Developers
Classifier: Intended Audience :: Science/Research
Classifier: Natural Language :: English
Classifier: Operating System :: MacOS :: MacOS X
Classifier: Operating System :: Microsoft :: Windows
Classifier: Operating System :: POSIX :: Linux
Classifier: Programming Language :: Python :: 3
Classifier: Programming Language :: Python :: 3.5
Classifier: Programming Language :: Python :: 3.6
Classifier: Programming Language :: Python :: 3.7
Classifier: Topic :: Scientific/Engineering :: Visualization
Requires-Dist: numpy (>=1.16.0)
Requires-Dist: scipy (>=1.1.0)
Requires-Dist: scikit-learn (>=0.19.1)
Requires-Dist: pandas (>=0.25)
Requires-Dist: joblib
Requires-Dist: scprep (>=1.0)
Requires-Dist: phate (>=1.0.0)
Requires-Dist: graphtools (>=1.5)
Requires-Dist: tasklogger (>=1.0)
Requires-Dist: matplotlib (>=3.0)
Provides-Extra: doc
Requires-Dist: sphinx (<=1.8.5) ; extra == 'doc'
Requires-Dist: sphinxcontrib-napoleon ; extra == 'doc'
Requires-Dist: autodocsumm ; extra == 'doc'
Requires-Dist: ipykernel ; extra == 'doc'
Requires-Dist: nbsphinx ; extra == 'doc'
Provides-Extra: test
Requires-Dist: nose2 ; extra == 'test'
Requires-Dist: coverage ; extra == 'test'
Requires-Dist: coveralls ; extra == 'test'
Requires-Dist: keras (>=2.2) ; extra == 'test'
Requires-Dist: tensorflow (<2.0,>=1.13) ; extra == 'test'
Requires-Dist: parameterized ; extra == 'test'
